README.rst
setup.cfg
setup.py
exopy_hqc_legacy/__init__.py
exopy_hqc_legacy/manifest.enaml
exopy_hqc_legacy/version.py
exopy_hqc_legacy.egg-info/PKG-INFO
exopy_hqc_legacy.egg-info/SOURCES.txt
exopy_hqc_legacy.egg-info/dependency_links.txt
exopy_hqc_legacy.egg-info/entry_points.txt
exopy_hqc_legacy.egg-info/not-zip-safe
exopy_hqc_legacy.egg-info/requires.txt
exopy_hqc_legacy.egg-info/top_level.txt
exopy_hqc_legacy/conversion/__init__.py
exopy_hqc_legacy/conversion/__main__.py
exopy_hqc_legacy/conversion/convert.py
exopy_hqc_legacy/conversion/ui.enaml
exopy_hqc_legacy/instruments/__init__.py
exopy_hqc_legacy/instruments/connections/__init__.py
exopy_hqc_legacy/instruments/connections/dll_serial_number_connection.enaml
exopy_hqc_legacy/instruments/drivers/__init__.py
exopy_hqc_legacy/instruments/drivers/dll_tools.py
exopy_hqc_legacy/instruments/drivers/driver_tools.py
exopy_hqc_legacy/instruments/drivers/visa_tools.py
exopy_hqc_legacy/instruments/drivers/dll/__init__.py
exopy_hqc_legacy/instruments/drivers/dll/alazar935x.py
exopy_hqc_legacy/instruments/drivers/dll/atsapi.py
exopy_hqc_legacy/instruments/drivers/dll/labbrick.py
exopy_hqc_legacy/instruments/drivers/dll/sp_adq14.py
exopy_hqc_legacy/instruments/drivers/visa/__init__.py
exopy_hqc_legacy/instruments/drivers/visa/agilent_multimeters.py
exopy_hqc_legacy/instruments/drivers/visa/agilent_pna.py
exopy_hqc_legacy/instruments/drivers/visa/agilent_psa.py
exopy_hqc_legacy/instruments/drivers/visa/agilent_psg_signal_generators.py
exopy_hqc_legacy/instruments/drivers/visa/anapico.py
exopy_hqc_legacy/instruments/drivers/visa/anritsu_signal_source.py
exopy_hqc_legacy/instruments/drivers/visa/cryomagnetics_cs4.py
exopy_hqc_legacy/instruments/drivers/visa/keithley_multimeters.py
exopy_hqc_legacy/instruments/drivers/visa/le_croy_64xi.py
exopy_hqc_legacy/instruments/drivers/visa/lock_in_sr72_series.py
exopy_hqc_legacy/instruments/drivers/visa/lock_in_sr830.py
exopy_hqc_legacy/instruments/drivers/visa/oxford_ips.py
exopy_hqc_legacy/instruments/drivers/visa/rohde_and_schwarz_signal_generators.py
exopy_hqc_legacy/instruments/drivers/visa/rohde_and_schwarz_vna.py
exopy_hqc_legacy/instruments/drivers/visa/rohde_and_schwarz_zva24.py
exopy_hqc_legacy/instruments/drivers/visa/tabor_awg.py
