Metadata-Version: 1.1
Name: exopy-hqc-legacy
Version: 0.1.0
Summary: Transitional package between HQCMeas and Exopy
Home-page: https://github.com/exopy/exopy_hqc_legacy
Author: see AUTHORS
Author-email: m.dartiailh@gmail.com
License: BSD
Download-URL: https://github.com/exopy/exopy_hqc_legacy/tarball/master
Keywords: experiment automation GUI
Platform: UNKNOWN
Classifier: Development Status :: 3 - Alpha
Classifier: License :: OSI Approved :: BSD License
Classifier: Natural Language :: English
Classifier: Operating System :: OS Independent
Classifier: Topic :: Scientific/Engineering :: Physics
Classifier: Programming Language :: Python :: 2.7
Classifier: Programming Language :: Python :: 3.5
Classifier: Programming Language :: Python :: 3.6
Requires: exopy
Requires: pyvisa
Requires: h5py
Requires: numpy
Requires: pyclibrary
